[
    {
        "classes": [
            {
                "className": "Task",
                "object": true,
                "qualifiedClassName": "Task",
                "signals": [
                    {
                        "access": "public",
                        "arguments": [
                            {
                                "name": "description",
                                "type": "QString"
                            }
                        ],
                        "name": "taskCompleted",
                        "returnType": "void"
                    }
                ],
                "superClasses": [
                    {
                        "access": "public",
                        "name": "QObject"
                    }
                ]
            }
        ],
        "inputFile": "task.h",
        "outputRevision": 68
    }
]
